MANIFEST.in
README.rst
setup.py
docs/HISTORY.txt
eea/__init__.py
eea.faceted.tool.egg-info/PKG-INFO
eea.faceted.tool.egg-info/SOURCES.txt
eea.faceted.tool.egg-info/dependency_links.txt
eea.faceted.tool.egg-info/entry_points.txt
eea.faceted.tool.egg-info/namespace_packages.txt
eea.faceted.tool.egg-info/not-zip-safe
eea.faceted.tool.egg-info/requires.txt
eea.faceted.tool.egg-info/top_level.txt
eea/faceted/__init__.py
eea/faceted/tool/README.txt
eea/faceted/tool/__init__.py
eea/faceted/tool/config.py
eea/faceted/tool/configure.zcml
eea/faceted/tool/interfaces.py
eea/faceted/tool/profiles.zcml
eea/faceted/tool/setuphandlers.py
eea/faceted/tool/tool.gif
eea/faceted/tool/tool.py
eea/faceted/tool/version.txt
eea/faceted/tool/browser/__init__.py
eea/faceted/tool/browser/configure.zcml
eea/faceted/tool/browser/app/__init__.py
eea/faceted/tool/browser/app/portaltype.py
eea/faceted/tool/browser/app/tool.py
eea/faceted/tool/browser/template/view.pt
eea/faceted/tool/docs/browser.txt
eea/faceted/tool/docs/exportimport.txt
eea/faceted/tool/docs/search.txt
eea/faceted/tool/docs/storage.txt
eea/faceted/tool/docs/vocabularies.txt
eea/faceted/tool/exportimport/__init__.py
eea/faceted/tool/exportimport/configure.zcml
eea/faceted/tool/exportimport/portaltype.py
eea/faceted/tool/exportimport/tool.py
eea/faceted/tool/profiles/default/componentregistry.xml
eea/faceted/tool/profiles/default/controlpanel.xml
eea/faceted/tool/profiles/default/eea.faceted.tool.txt
eea/faceted/tool/profiles/default/faceted.xml
eea/faceted/tool/profiles/default/metadata.xml
eea/faceted/tool/profiles/default/toolset.xml
eea/faceted/tool/search/__init__.py
eea/faceted/tool/search/catalog.py
eea/faceted/tool/search/configure.zcml
eea/faceted/tool/storage/__init__.py
eea/faceted/tool/storage/configure.zcml
eea/faceted/tool/storage/namechooser.py
eea/faceted/tool/storage/portaltype.py
eea/faceted/tool/tests/__init__.py
eea/faceted/tool/tests/base.py
eea/faceted/tool/tests/test_doctests.py
eea/faceted/tool/upgrades/__init__.py
eea/faceted/tool/upgrades/configure.zcml